[{"Id":790298640454,"Title":"Associate, FP&A, Korea Content","Team":"Not Specified","Subteam":"Finance, Strategy, And Accounting","Location":"Seoul, Korea, Republic of","Posting Date Time":"2024-08-28T15:05:00.000Z","Job URL":"https:\/\/jobs.netflix.com\/jobs\/790298640454","Posting Date":"2024-08-28T00:00:00.000","Job Status":"Open","Days Active":4},{"Id":790298792200,"Title":"Producer, Product Creative Studio - EMEA","Team":"Not Specified","Subteam":"Program Management","Location":"Amsterdam, Netherlands","Posting Date Time":"2024-08-30T18:05:00.000Z","Job URL":"https:\/\/jobs.netflix.com\/jobs\/790298792200","Posting Date":"2024-08-30T00:00:00.000","Job Status":"Open","Days Active":2}]