[{"Id":790299317904,"Title":"Creative Assistant, Nonfiction, Africa\/ Arabic","Team":"Not Specified","Subteam":"Content Development & Acquisition","Location":"Amsterdam, Netherlands","Posting Date Time":"2024-09-30T18:05:00.000Z","Job URL":"https:\/\/jobs.netflix.com\/jobs\/790299317904","Posting Date":"2024-09-30T00:00:00.000","Job Status":"Open","Days Active":1},{"Id":790299324555,"Title":"Administrative Assistant, Product Management","Team":"Not Specified","Subteam":"Administration","Location":"Los Gatos, California, United States of America","Posting Date Time":"2024-09-30T22:05:00.000Z","Job URL":"https:\/\/jobs.netflix.com\/jobs\/790299324555","Posting Date":"2024-09-30T00:00:00.000","Job Status":"Open","Days Active":1}]